{
  "input_rows": 248072,
  "output_rows": 239860,
  "rows_removed_total": 8212,
  "removed_missing_submission_id": 0,
  "removed_duplicate_ids": 0,
  "removed_bot_mod_rows": 8194,
  "removed_composite_duplicates": 18,
  "composite_duplicates_dropped": true,
  "unique_submission_ids_needed": 8838,
  "unique_comment_ids_after_cleaning": 239860,
  "columns_in_output": [
    "id",
    "created_utc",
    "date_utc",
    "source_type",
    "subreddit",
    "author",
    "score",
    "title",
    "body_text",
    "raw_text",
    "permalink",
    "link_id",
    "parent_id",
    "submission_id",
    "matched_tickers",
    "matched_terms",
    "match_sources",
    "match_count",
    "is_multi_match",
    "match_confidence",
    "needs_context_filter",
    "thread_position"
  ]
}